stest/__init__.py
stest/__main__.py
stest/fixed_field.py
stest/main.py
stest/conf/__init__.py
stest/conf/global_settings.py
stest/conf/image_show.py
stest/core/__init__.py
stest/core/abstract_data_provider.py
stest/core/abstract_testcase.py
stest/core/depends.py
stest/core/errors.py
stest/core/report_builder.py
stest/core/result_formatter.py
stest/core/seven_data_provider.py
stest/core/seven_loader.py
stest/core/seven_result.py
stest/core/seven_runner.py
stest/core/test_wrapper.py
stest/dm/__init__.py
stest/dm/driver_cache.py
stest/dm/driver_manager.py
stest/dm/playwright_driver.py
stest/dm/wechat_minium_proxy.py
stest/dm/win_app_driver_helper.py
stest/hook/__init__.py
stest/hook/impl.py
stest/hook/policy.py
stest/hook/stage.py
stest/pylibs/__init__.py
stest/pylibs/lazy_libs.py
stest/pylibs/python_imp.py
stest/report/__init__.py
stest/report/htmltemplate.py
stest/report/jenkins_junit_xml_template.py
stest/report/html/__init__.py
stest/report/html/elements.py
stest/report/html/tags.py
stest/report/resources/bitbug_favicon.ico
stest/report/resources/jquery-1.11.0.min.js
stest/report/resources/main.js
stest/report/resources/seventester.ico
stest/report/resources/style.css
stest/report/widgets/__init__.py
stest/report/widgets/piechart.py
stest/report/widgets/tables.py
stest/samples/CalculationTest.xlsx
stest/samples/__init__.py
stest/samples/calculation_test.py
stest/samples/dependency_test.py
stest/testobjs/__init__.py
stest/testobjs/abstract_minium_page.py
stest/testobjs/abstract_page.py
stest/testobjs/abstract_playwright_page.py
stest/testobjs/useful/__init__.py
stest/testobjs/useful/table_locator.py
stest/utils/__init__.py
stest/utils/attrs_manager.py
stest/utils/attrs_marker.py
stest/utils/autoit_helper.py
stest/utils/dict2object.py
stest/utils/excel_file_reader.py
stest/utils/function_mapper.py
stest/utils/import_helper.py
stest/utils/lazy_obj.py
stest/utils/pre_map.py
stest/utils/screenshot_capturer.py
stest/utils/sutils.py
stest/utils/timedelta_displayer.py
stest-1.0.7.dist-info/LICENSE
stest-1.0.7.dist-info/METADATA
stest-1.0.7.dist-info/WHEEL
stest-1.0.7.dist-info/top_level.txt
stest-1.0.7.dist-info/RECORD
