Metadata-Version: 2.1
Name: stest
Version: 1.0.7
Summary: 更友好、更灵活的编写、管理与运行测试，生成更加美观的独立单文件HTML报告。内置参数化测试数据存取方案，省去设计的烦恼，节省更多的时间，从而更快的投入到编写用例阶段
Home-page: https://github.com/hotswwkyo/stest
Author: 思文伟
Author-email: hotswwkyo@qq.com
License: MIT
Platform: UNKNOWN
Classifier: Programming Language :: Python :: 3
Classifier: License :: OSI Approved :: MIT License
Classifier: Natural Language :: Chinese (Simplified)
Classifier: Operating System :: OS Independent
Requires-Python: >=3
Requires-Dist: xlrd (==1.2.0)
